bugswarm/common/__init__.py
bugswarm/common/credentials.py
bugswarm/common/diff_calculator.py
bugswarm/common/filter_reasons.py
bugswarm/common/github_wrapper.py
bugswarm/common/json.py
bugswarm/common/log.py
bugswarm/common/log_downloader.py
bugswarm/common/outdated.py
bugswarm/common/shell_wrapper.py
bugswarm/common/travis_wrapper.py
bugswarm/common/unsupported_actions.py
bugswarm/common/utils.py
bugswarm/common/artifact_processing/__init__.py
bugswarm/common/artifact_processing/runners.py
bugswarm/common/artifact_processing/utils.py
bugswarm/common/decorators/__init__.py
bugswarm/common/decorators/classproperty.py
bugswarm/common/rest_api/__init__.py
bugswarm/common/rest_api/database_api.py
bugswarm/common/rest_api/exceptions.py
bugswarm_common-2024.8.26.dist-info/LICENSE
bugswarm_common-2024.8.26.dist-info/METADATA
bugswarm_common-2024.8.26.dist-info/WHEEL
bugswarm_common-2024.8.26.dist-info/top_level.txt
bugswarm_common-2024.8.26.dist-info/RECORD
