Metadata-Version: 2.1
Name: bugswarm-common
Version: 2024.8.26
Summary: Library of modules used throughout the BugSwarm toolset
Home-page: https://github.com/BugSwarm/bugswarm
Author: BugSwarm
Author-email: dev.bugswarm@gmail.com
Classifier: Programming Language :: Python :: 3
Classifier: License :: OSI Approved :: BSD License
License-File: LICENSE
Requires-Dist: requests <=2.31,>=2.20.0
Requires-Dist: CacheControl ==0.12.3
Requires-Dist: requests-cache ==0.4.13
Requires-Dist: charset-normalizer <4,>=2
